kihara/__init__.py
kihara/__main__.py
kihara/_cachedir.py
kihara/_locale.py
kihara/index.py
kihara/link.py
kihara/utils.py
kihara/version.py
kihara-0.2.0.dist-info/METADATA
kihara-0.2.0.dist-info/WHEEL
kihara-0.2.0.dist-info/entry_points.txt
kihara-0.2.0.dist-info/top_level.txt
kihara-0.2.0.dist-info/RECORD
