Metadata-Version: 2.1
Name: kihara
Version: 0.2.0
Summary: Something
Home-page: https://github.com/louisdevie/kihara
Author: Louis DEVIE
Author-email: louisdevie.contact@gmail.com
License: UNKNOWN
Platform: UNKNOWN
Classifier: Programming Language :: Python :: 3
Classifier: Operating System :: OS Independent
Requires-Python: >=3.8
